[{"similarity": 1.0, "filename": "PRIV-3978"}, {"similarity": 0.708, "filename": "PRIV-3982"}, {"similarity": 0.7021, "filename": "PRIV-4665"}, {"similarity": 0.6987, "filename": "GKM-3603"}, {"similarity": 0.695, "filename": "GKM-3542"}, {"similarity": 0.6903, "filename": "GKM-3650"}, {"similarity": 0.6899, "filename": "PRIV-4622"}, {"similarity": 0.6896, "filename": "PRIV-4439"}, {"similarity": 0.6894, "filename": "GKM-3828"}, {"similarity": 0.6889, "filename": "PRIV-4332"}, {"similarity": 0.6848, "filename": "PRIV-4325"}, {"similarity": 0.6847, "filename": "GKM-3756"}, {"similarity": 0.6846, "filename": "NM-3264"}, {"similarity": 0.6825, "filename": "GKM-3623"}, {"similarity": 0.6823, "filename": "GKM-3684"}, {"similarity": 0.6818, "filename": "PRIV-4273"}, {"similarity": 0.6811, "filename": "PRIV-4474"}, {"similarity": 0.6779, "filename": "NM-3262"}, {"similarity": 0.6759, "filename": "PRIV-4537"}, {"similarity": 0.6751, "filename": "PRIV-4381"}, {"similarity": 0.6749, "filename": "PRIV-4520"}, {"similarity": 0.6702, "filename": "PRIV-4372"}, {"similarity": 0.6702, "filename": "PRIV-4739"}, {"similarity": 0.6686, "filename": "PRIV-4044"}, {"similarity": 0.6664, "filename": "GKM-3499"}, {"similarity": 0.6662, "filename": "PRIV-4057"}, {"similarity": 0.6654, "filename": "PRIV-4300"}, {"similarity": 0.6644, "filename": "PRIV-4115"}, {"similarity": 0.663, "filename": "PRIV-4346"}, {"similarity": 0.6629, "filename": "GKM-3601"}]