[{"similarity": 1.0, "filename": "GKM-3582"}, {"similarity": 0.8479, "filename": "GKM-3616"}, {"similarity": 0.8475, "filename": "GKM-3722"}, {"similarity": 0.8197, "filename": "GKM-3598"}, {"similarity": 0.8163, "filename": "NM-3170"}, {"similarity": 0.8087, "filename": "GKM-3662"}, {"similarity": 0.7976, "filename": "GKM-3790"}, {"similarity": 0.7913, "filename": "GKM-3584"}, {"similarity": 0.7892, "filename": "GKM-3721"}, {"similarity": 0.785, "filename": "NM-3165"}, {"similarity": 0.7759, "filename": "GKM-3804"}, {"similarity": 0.7752, "filename": "GKM-3797"}, {"similarity": 0.774, "filename": "GKM-3611"}, {"similarity": 0.7729, "filename": "GKM-3752"}, {"similarity": 0.7692, "filename": "GKM-3796"}, {"similarity": 0.7681, "filename": "GKM-3829"}, {"similarity": 0.7678, "filename": "NM-3164"}, {"similarity": 0.767, "filename": "NM-3136"}, {"similarity": 0.7656, "filename": "GKM-3630"}, {"similarity": 0.7654, "filename": "GKM-3580"}, {"similarity": 0.7652, "filename": "GKM-3711"}, {"similarity": 0.7648, "filename": "GKM-3627"}, {"similarity": 0.7633, "filename": "GKM-3699"}, {"similarity": 0.7616, "filename": "GKM-3810"}, {"similarity": 0.7595, "filename": "GKM-3604"}, {"similarity": 0.7594, "filename": "GKM-3597"}, {"similarity": 0.7586, "filename": "GKM-3640"}, {"similarity": 0.7543, "filename": "GKM-3702"}, {"similarity": 0.7543, "filename": "GKM-3801"}, {"similarity": 0.7539, "filename": "GKM-3558"}]