[{"filename": "GKM-3833", "similarity": 1.0}, {"filename": "NM-3108", "similarity": 0.7561}, {"filename": "PRIV-4062", "similarity": 0.7335}, {"filename": "GKM-3727", "similarity": 0.729}, {"filename": "GKM-3472", "similarity": 0.7237}, {"filename": "NM-3107", "similarity": 0.7016}, {"filename": "PRIV-4012", "similarity": 0.7008}, {"filename": "GKM-3473", "similarity": 0.6955}, {"filename": "PRIV-4065", "similarity": 0.6946}, {"filename": "GKM-3608", "similarity": 0.6845}, {"filename": "PRIV-4067", "similarity": 0.6734}, {"filename": "GKM-3471", "similarity": 0.6726}, {"filename": "GKM-3552", "similarity": 0.6678}, {"filename": "GKM-3798", "similarity": 0.6669}, {"filename": "NM-3187", "similarity": 0.664}, {"filename": "GKM-3749", "similarity": 0.6614}, {"filename": "GKM-3545", "similarity": 0.6582}, {"filename": "GKM-3615", "similarity": 0.6579}, {"filename": "PRIV-3927", "similarity": 0.6529}, {"filename": "GKM-3461", "similarity": 0.6511}, {"filename": "PRIV-4022", "similarity": 0.6489}, {"filename": "GKM-3476", "similarity": 0.645}, {"filename": "GKM-3565", "similarity": 0.6429}, {"filename": "GKM-3836", "similarity": 0.6424}, {"filename": "PRIV-3997", "similarity": 0.6415}, {"filename": "PRIV-4028", "similarity": 0.6404}, {"filename": "NM-3222", "similarity": 0.6402}, {"filename": "NM-3131", "similarity": 0.6393}, {"filename": "GKM-3474", "similarity": 0.6372}, {"filename": "PRIV-3946", "similarity": 0.6369}]