[{"similarity": 1.0, "filename": "GKM-3751"}, {"similarity": 0.7356, "filename": "GKM-3542"}, {"similarity": 0.7291, "filename": "PRIV-4343"}, {"similarity": 0.7273, "filename": "PRIV-3989"}, {"similarity": 0.7259, "filename": "PRIV-4304"}, {"similarity": 0.7235, "filename": "PRIV-4140"}, {"similarity": 0.7219, "filename": "PRIV-3987"}, {"similarity": 0.7133, "filename": "NM-3125"}, {"similarity": 0.7112, "filename": "PRIV-4548"}, {"similarity": 0.7105, "filename": "PRIV-4391"}, {"similarity": 0.708, "filename": "PRIV-4614"}, {"similarity": 0.7064, "filename": "PRIV-4736"}, {"similarity": 0.7055, "filename": "GKM-3680"}, {"similarity": 0.7043, "filename": "PRIV-4561"}, {"similarity": 0.7034, "filename": "PRIV-4665"}, {"similarity": 0.7026, "filename": "NM-3172"}, {"similarity": 0.7014, "filename": "PRIV-4721"}, {"similarity": 0.7006, "filename": "NM-3191"}, {"similarity": 0.7005, "filename": "PRIV-4570"}, {"similarity": 0.7001, "filename": "NM-3282"}, {"similarity": 0.7, "filename": "NM-3280"}, {"similarity": 0.6991, "filename": "GKM-3725"}, {"similarity": 0.6991, "filename": "NM-3279"}, {"similarity": 0.6985, "filename": "GKM-3493"}, {"similarity": 0.6979, "filename": "PRIV-4375"}, {"similarity": 0.6978, "filename": "GKM-3553"}, {"similarity": 0.6975, "filename": "GKM-3563"}, {"similarity": 0.6968, "filename": "GKM-3509"}, {"similarity": 0.6965, "filename": "NM-3281"}, {"similarity": 0.6959, "filename": "NM-3182"}]