[{"filename": "GKM-3735", "similarity": 1.0}, {"filename": "GKM-3693", "similarity": 0.7441}, {"filename": "NM-3131", "similarity": 0.7272}, {"filename": "GKM-3698", "similarity": 0.722}, {"filename": "GKM-3743", "similarity": 0.713}, {"filename": "GKM-3798", "similarity": 0.7045}, {"filename": "GUB-3361", "similarity": 0.7014}, {"filename": "GUB-2132", "similarity": 0.6928}, {"filename": "GKM-3471", "similarity": 0.6914}, {"filename": "GKM-3490", "similarity": 0.6913}, {"filename": "GUB-3389", "similarity": 0.6851}, {"filename": "NM-3216", "similarity": 0.6846}, {"filename": "PRIV-4031", "similarity": 0.6843}, {"filename": "GKM-3607", "similarity": 0.6839}, {"filename": "NM-3178", "similarity": 0.6815}, {"filename": "PRIV-3918", "similarity": 0.6788}, {"filename": "PRIV-3921", "similarity": 0.6746}, {"filename": "GUB-3359", "similarity": 0.674}, {"filename": "GKM-3670", "similarity": 0.6714}, {"filename": "PRIV-4022", "similarity": 0.6702}, {"filename": "GKM-3664", "similarity": 0.6682}, {"filename": "PRIV-3963", "similarity": 0.6681}, {"filename": "PRIV-4041", "similarity": 0.6662}, {"filename": "NM-3121", "similarity": 0.6652}, {"filename": "GKM-3700", "similarity": 0.6648}, {"filename": "GKM-3690", "similarity": 0.6641}, {"filename": "PRIV-3943", "similarity": 0.6639}, {"filename": "GKM-3812", "similarity": 0.6636}, {"filename": "GKM-3463", "similarity": 0.6626}, {"filename": "NM-3107", "similarity": 0.6619}]