[{"filename": "GKM-3529", "similarity": 1.0}, {"filename": "GKM-3528", "similarity": 0.7407}, {"filename": "GKM-3527", "similarity": 0.7068}, {"filename": "GKM-3495", "similarity": 0.6963}, {"filename": "PRIV-4472", "similarity": 0.6743}, {"filename": "GKM-3512", "similarity": 0.673}, {"filename": "GKM-3509", "similarity": 0.6706}, {"filename": "GKM-3502", "similarity": 0.6682}, {"filename": "PRIV-4005", "similarity": 0.6665}, {"filename": "NM-3262", "similarity": 0.664}, {"filename": "GKM-3513", "similarity": 0.6631}, {"filename": "GKM-3532", "similarity": 0.6506}, {"filename": "PRIV-3923", "similarity": 0.6489}, {"filename": "GKM-3499", "similarity": 0.6486}, {"filename": "GKM-3498", "similarity": 0.6479}, {"filename": "NM-3285", "similarity": 0.6461}, {"filename": "PRIV-4162", "similarity": 0.6448}, {"filename": "GKM-3519", "similarity": 0.6425}, {"filename": "GKM-3522", "similarity": 0.6387}, {"filename": "GKM-3511", "similarity": 0.6378}, {"filename": "PRIV-4141", "similarity": 0.6371}, {"filename": "GKM-3510", "similarity": 0.6348}, {"filename": "PRIV-4294", "similarity": 0.6348}, {"filename": "PRIV-4242", "similarity": 0.6342}, {"filename": "PRIV-4552", "similarity": 0.6324}, {"filename": "PRIV-4167", "similarity": 0.6316}, {"filename": "GKM-3503", "similarity": 0.6305}, {"filename": "GKM-3676", "similarity": 0.6296}, {"filename": "NM-3253", "similarity": 0.6281}, {"filename": "PRIV-4151", "similarity": 0.6279}]