[{"filename": "GUB-3359", "similarity": 1.0}, {"filename": "GUB-3357", "similarity": 0.7645}, {"filename": "NM-3141", "similarity": 0.7456}, {"filename": "GUB-3361", "similarity": 0.7415}, {"filename": "GKM-3700", "similarity": 0.7389}, {"filename": "GUB-3365", "similarity": 0.7362}, {"filename": "PRIV-3983", "similarity": 0.7311}, {"filename": "GUB-3389", "similarity": 0.7303}, {"filename": "GUB-3391", "similarity": 0.7288}, {"filename": "NM-3171", "similarity": 0.7244}, {"filename": "NM-3203", "similarity": 0.7157}, {"filename": "GUB-3363", "similarity": 0.7138}, {"filename": "NM-3158", "similarity": 0.7135}, {"filename": "GKM-3695", "similarity": 0.7081}, {"filename": "PRIV-4041", "similarity": 0.7067}, {"filename": "GUB-3393", "similarity": 0.7049}, {"filename": "GKM-3731", "similarity": 0.7032}, {"filename": "PRIV-3944", "similarity": 0.7024}, {"filename": "GKM-3725", "similarity": 0.7018}, {"filename": "PRIV-3945", "similarity": 0.6994}, {"filename": "NM-3205", "similarity": 0.6989}, {"filename": "GUB-3387", "similarity": 0.6856}, {"filename": "GKM-3791", "similarity": 0.6814}, {"filename": "NM-3125", "similarity": 0.6798}, {"filename": "GKM-3822", "similarity": 0.6785}, {"filename": "GKM-3798", "similarity": 0.678}, {"filename": "PRIV-3987", "similarity": 0.6762}, {"filename": "PRIV-3993", "similarity": 0.6761}, {"filename": "PRIV-3948", "similarity": 0.6758}, {"filename": "GKM-3693", "similarity": 0.6755}]