[{"similarity": 1.0, "filename": "GUB-3361"}, {"similarity": 0.7415, "filename": "GUB-3359"}, {"similarity": 0.7345, "filename": "NM-3141"}, {"similarity": 0.7202, "filename": "GUB-3365"}, {"similarity": 0.7172, "filename": "GUB-3363"}, {"similarity": 0.717, "filename": "GUB-3391"}, {"similarity": 0.717, "filename": "PRIV-4382"}, {"similarity": 0.7165, "filename": "PRIV-4170"}, {"similarity": 0.7155, "filename": "PRIV-3944"}, {"similarity": 0.7133, "filename": "GUB-3389"}, {"similarity": 0.7106, "filename": "GUB-3393"}, {"similarity": 0.71, "filename": "PRIV-4152"}, {"similarity": 0.7091, "filename": "GUB-3357"}, {"similarity": 0.7053, "filename": "PRIV-4642"}, {"similarity": 0.7026, "filename": "PRIV-4165"}, {"similarity": 0.7025, "filename": "PRIV-4253"}, {"similarity": 0.7019, "filename": "PRIV-4331"}, {"similarity": 0.7018, "filename": "PRIV-4639"}, {"similarity": 0.7014, "filename": "GKM-3735"}, {"similarity": 0.7003, "filename": "GKM-3798"}, {"similarity": 0.6971, "filename": "PRIV-4301"}, {"similarity": 0.6963, "filename": "PRIV-3924"}, {"similarity": 0.6943, "filename": "GUB-2132"}, {"similarity": 0.6905, "filename": "NM-3158"}, {"similarity": 0.69, "filename": "PRIV-4178"}, {"similarity": 0.6899, "filename": "PRIV-4489"}, {"similarity": 0.6894, "filename": "PRIV-4414"}, {"similarity": 0.6892, "filename": "PRIV-4193"}, {"similarity": 0.6892, "filename": "PRIV-4368"}, {"similarity": 0.6885, "filename": "GKM-3776"}]