[{"filename": "NM-3173", "similarity": 1.0}, {"filename": "NM-3225", "similarity": 0.7445}, {"filename": "PRIV-3974", "similarity": 0.7305}, {"filename": "GKM-3688", "similarity": 0.7215}, {"filename": "PRIV-4308", "similarity": 0.7127}, {"filename": "PRIV-4071", "similarity": 0.7116}, {"filename": "PRIV-4330", "similarity": 0.703}, {"filename": "PRIV-4503", "similarity": 0.7027}, {"filename": "PRIV-4047", "similarity": 0.6996}, {"filename": "PRIV-3958", "similarity": 0.6976}, {"filename": "PRIV-4021", "similarity": 0.6972}, {"filename": "PRIV-4058", "similarity": 0.6969}, {"filename": "PRIV-3920", "similarity": 0.6966}, {"filename": "PRIV-4389", "similarity": 0.6964}, {"filename": "PRIV-4428", "similarity": 0.6947}, {"filename": "PRIV-4328", "similarity": 0.6913}, {"filename": "GKM-3744", "similarity": 0.6818}, {"filename": "PRIV-4097", "similarity": 0.6775}, {"filename": "PRIV-4580", "similarity": 0.6743}, {"filename": "PRIV-4573", "similarity": 0.6725}, {"filename": "PRIV-4309", "similarity": 0.6724}, {"filename": "PRIV-4068", "similarity": 0.6695}, {"filename": "NM-3092", "similarity": 0.669}, {"filename": "PRIV-3969", "similarity": 0.666}, {"filename": "PRIV-4131", "similarity": 0.6645}, {"filename": "PRIV-4599", "similarity": 0.6641}, {"filename": "PRIV-3912", "similarity": 0.6638}, {"filename": "PRIV-4015", "similarity": 0.6633}, {"filename": "PRIV-4222", "similarity": 0.6631}, {"filename": "PRIV-4300", "similarity": 0.6628}]