[{"similarity": 1.0, "filename": "NM-3220"}, {"similarity": 0.754, "filename": "NM-3169"}, {"similarity": 0.729, "filename": "GKM-3491"}, {"similarity": 0.7237, "filename": "NM-3165"}, {"similarity": 0.7152, "filename": "NM-3142"}, {"similarity": 0.7085, "filename": "NM-3164"}, {"similarity": 0.7066, "filename": "GKM-3542"}, {"similarity": 0.7062, "filename": "NM-3168"}, {"similarity": 0.7033, "filename": "NM-3201"}, {"similarity": 0.7022, "filename": "NM-3167"}, {"similarity": 0.7012, "filename": "NM-3166"}, {"similarity": 0.6967, "filename": "GKM-3628"}, {"similarity": 0.6965, "filename": "NM-3200"}, {"similarity": 0.6913, "filename": "GUB-760"}, {"similarity": 0.6899, "filename": "NM-3092"}, {"similarity": 0.6866, "filename": "PRIV-3908"}, {"similarity": 0.6852, "filename": "GKM-3690"}, {"similarity": 0.6813, "filename": "GUB-765"}, {"similarity": 0.6767, "filename": "NM-3207"}, {"similarity": 0.6751, "filename": "GKM-3590"}, {"similarity": 0.6741, "filename": "PRIV-3987"}, {"similarity": 0.674, "filename": "NM-3281"}, {"similarity": 0.6738, "filename": "GKM-3663"}, {"similarity": 0.6733, "filename": "NM-3280"}, {"similarity": 0.673, "filename": "NM-3206"}, {"similarity": 0.6715, "filename": "PRIV-3909"}, {"similarity": 0.6714, "filename": "PRIV-3986"}, {"similarity": 0.6677, "filename": "GKM-3748"}, {"similarity": 0.6663, "filename": "NM-3183"}, {"similarity": 0.6657, "filename": "NM-3182"}]