[{"similarity": 1.0, "filename": "PRIV-3915"}, {"similarity": 0.7322, "filename": "PRIV-4587"}, {"similarity": 0.7298, "filename": "NM-3171"}, {"similarity": 0.7298, "filename": "PRIV-4324"}, {"similarity": 0.7273, "filename": "GKM-3684"}, {"similarity": 0.7229, "filename": "PRIV-4721"}, {"similarity": 0.7193, "filename": "PRIV-4149"}, {"similarity": 0.7159, "filename": "PRIV-4627"}, {"similarity": 0.7144, "filename": "PRIV-3916"}, {"similarity": 0.7114, "filename": "GKM-3544"}, {"similarity": 0.7107, "filename": "PRIV-4108"}, {"similarity": 0.709, "filename": "PRIV-4561"}, {"similarity": 0.7048, "filename": "NM-3097"}, {"similarity": 0.7042, "filename": "PRIV-4730"}, {"similarity": 0.7038, "filename": "PRIV-4665"}, {"similarity": 0.7037, "filename": "PRIV-3921"}, {"similarity": 0.7028, "filename": "PRIV-4548"}, {"similarity": 0.7018, "filename": "GKM-3564"}, {"similarity": 0.6981, "filename": "PRIV-4220"}, {"similarity": 0.6943, "filename": "NM-3202"}, {"similarity": 0.6908, "filename": "NM-3164"}, {"similarity": 0.6904, "filename": "PRIV-4756"}, {"similarity": 0.6886, "filename": "NM-3094"}, {"similarity": 0.6886, "filename": "PRIV-4639"}, {"similarity": 0.6885, "filename": "GKM-3693"}, {"similarity": 0.6866, "filename": "PRIV-4141"}, {"similarity": 0.6853, "filename": "GKM-3583"}, {"similarity": 0.6852, "filename": "PRIV-3914"}, {"similarity": 0.6848, "filename": "PRIV-4524"}, {"similarity": 0.6847, "filename": "PRIV-3987"}]