[{"filename": "PRIV-4059", "similarity": 1.0}, {"filename": "PRIV-4123", "similarity": 0.7431}, {"filename": "PRIV-4561", "similarity": 0.7415}, {"filename": "PRIV-4009", "similarity": 0.7312}, {"filename": "PRIV-4417", "similarity": 0.7308}, {"filename": "PRIV-4219", "similarity": 0.7289}, {"filename": "PRIV-4486", "similarity": 0.7286}, {"filename": "GKM-3625", "similarity": 0.7279}, {"filename": "PRIV-4601", "similarity": 0.7273}, {"filename": "PRIV-4466", "similarity": 0.727}, {"filename": "GKM-3619", "similarity": 0.7258}, {"filename": "PRIV-4045", "similarity": 0.7233}, {"filename": "GKM-3812", "similarity": 0.7231}, {"filename": "PRIV-4220", "similarity": 0.7217}, {"filename": "PRIV-4299", "similarity": 0.7202}, {"filename": "GKM-3631", "similarity": 0.7192}, {"filename": "NM-3127", "similarity": 0.719}, {"filename": "GKM-3471", "similarity": 0.7185}, {"filename": "PRIV-3940", "similarity": 0.7185}, {"filename": "PRIV-4183", "similarity": 0.7172}, {"filename": "PRIV-4048", "similarity": 0.7171}, {"filename": "PRIV-3954", "similarity": 0.7161}, {"filename": "GKM-3588", "similarity": 0.7158}, {"filename": "PRIV-4480", "similarity": 0.7144}, {"filename": "PRIV-3985", "similarity": 0.7137}, {"filename": "GKM-3594", "similarity": 0.7127}, {"filename": "GKM-3607", "similarity": 0.7115}, {"filename": "PRIV-4206", "similarity": 0.7115}, {"filename": "PRIV-4149", "similarity": 0.7113}, {"filename": "NM-3121", "similarity": 0.7111}]