[{"similarity": 1.0, "filename": "PRIV-4349"}, {"similarity": 0.6893, "filename": "PRIV-4648"}, {"similarity": 0.6859, "filename": "PRIV-4420"}, {"similarity": 0.676, "filename": "NM-3187"}, {"similarity": 0.6661, "filename": "PRIV-4516"}, {"similarity": 0.6659, "filename": "PRIV-4507"}, {"similarity": 0.6536, "filename": "PRIV-4314"}, {"similarity": 0.649, "filename": "NM-3121"}, {"similarity": 0.6477, "filename": "PRIV-4758"}, {"similarity": 0.6465, "filename": "GKM-3798"}, {"similarity": 0.6447, "filename": "GKM-3635"}, {"similarity": 0.6417, "filename": "PRIV-4237"}, {"similarity": 0.6403, "filename": "PRIV-4315"}, {"similarity": 0.6396, "filename": "NM-3271"}, {"similarity": 0.6388, "filename": "PRIV-4154"}, {"similarity": 0.6387, "filename": "NM-3107"}, {"similarity": 0.6373, "filename": "PRIV-4704"}, {"similarity": 0.6349, "filename": "GKM-3664"}, {"similarity": 0.6347, "filename": "GKM-3467"}, {"similarity": 0.6343, "filename": "PRIV-4395"}, {"similarity": 0.6338, "filename": "GKM-3607"}, {"similarity": 0.6334, "filename": "PRIV-4313"}, {"similarity": 0.6325, "filename": "NM-3265"}, {"similarity": 0.6295, "filename": "PRIV-3958"}, {"similarity": 0.6282, "filename": "GKM-3473"}, {"similarity": 0.6277, "filename": "GKM-3735"}, {"similarity": 0.6272, "filename": "GKM-3654"}, {"similarity": 0.6271, "filename": "PRIV-4074"}, {"similarity": 0.6264, "filename": "NM-3178"}, {"similarity": 0.6258, "filename": "GKM-3608"}]