[{"similarity": 1.0, "filename": "PRIV-4721"}, {"similarity": 0.7598, "filename": "PRIV-4587"}, {"similarity": 0.7435, "filename": "PRIV-3987"}, {"similarity": 0.7305, "filename": "PRIV-4213"}, {"similarity": 0.7268, "filename": "PRIV-4191"}, {"similarity": 0.7265, "filename": "PRIV-4402"}, {"similarity": 0.7229, "filename": "PRIV-3915"}, {"similarity": 0.7229, "filename": "PRIV-4482"}, {"similarity": 0.7222, "filename": "GKM-3510"}, {"similarity": 0.7213, "filename": "GKM-3618"}, {"similarity": 0.7184, "filename": "PRIV-4135"}, {"similarity": 0.7146, "filename": "GKM-3690"}, {"similarity": 0.7119, "filename": "PRIV-4376"}, {"similarity": 0.7115, "filename": "PRIV-4707"}, {"similarity": 0.7114, "filename": "PRIV-4225"}, {"similarity": 0.7105, "filename": "NM-3094"}, {"similarity": 0.7104, "filename": "NM-3178"}, {"similarity": 0.7098, "filename": "GKM-3511"}, {"similarity": 0.7087, "filename": "GKM-3693"}, {"similarity": 0.7087, "filename": "PRIV-4167"}, {"similarity": 0.7087, "filename": "GKM-3828"}, {"similarity": 0.7081, "filename": "GKM-3695"}, {"similarity": 0.7057, "filename": "PRIV-4561"}, {"similarity": 0.7049, "filename": "PRIV-4739"}, {"similarity": 0.7043, "filename": "GKM-3590"}, {"similarity": 0.7031, "filename": "PRIV-4583"}, {"similarity": 0.7021, "filename": "PRIV-4155"}, {"similarity": 0.7017, "filename": "PRIV-4710"}, {"similarity": 0.7015, "filename": "PRIV-4150"}, {"similarity": 0.7014, "filename": "GKM-3751"}]