[{"similarity": 1.0, "filename": "PRIV-4197"}, {"similarity": 0.8255, "filename": "PRIV-4213"}, {"similarity": 0.7942, "filename": "PRIV-4204"}, {"similarity": 0.7841, "filename": "GKM-3590"}, {"similarity": 0.7822, "filename": "PRIV-4215"}, {"similarity": 0.7638, "filename": "PRIV-4301"}, {"similarity": 0.7635, "filename": "GKM-3605"}, {"similarity": 0.7597, "filename": "PRIV-4745"}, {"similarity": 0.7579, "filename": "PRIV-4193"}, {"similarity": 0.7502, "filename": "GKM-3463"}, {"similarity": 0.7498, "filename": "PRIV-4139"}, {"similarity": 0.7449, "filename": "PRIV-4191"}, {"similarity": 0.7414, "filename": "PRIV-4178"}, {"similarity": 0.7385, "filename": "PRIV-3914"}, {"similarity": 0.7374, "filename": "GKM-3710"}, {"similarity": 0.737, "filename": "NM-3140"}, {"similarity": 0.7346, "filename": "PRIV-4639"}, {"similarity": 0.7338, "filename": "NM-3157"}, {"similarity": 0.7332, "filename": "GKM-3693"}, {"similarity": 0.7331, "filename": "PRIV-3983"}, {"similarity": 0.7317, "filename": "PRIV-4207"}, {"similarity": 0.7305, "filename": "PRIV-4201"}, {"similarity": 0.724, "filename": "PRIV-4205"}, {"similarity": 0.7231, "filename": "PRIV-4360"}, {"similarity": 0.7224, "filename": "PRIV-4302"}, {"similarity": 0.7222, "filename": "GKM-3690"}, {"similarity": 0.7214, "filename": "PRIV-4196"}, {"similarity": 0.7206, "filename": "GKM-3548"}, {"similarity": 0.7192, "filename": "GKM-3464"}, {"similarity": 0.7187, "filename": "PRIV-4108"}]