[{"similarity": 1.0, "filename": "PRIV-4221"}, {"similarity": 0.7833, "filename": "GKM-3779"}, {"similarity": 0.7657, "filename": "PRIV-4586"}, {"similarity": 0.757, "filename": "PRIV-4497"}, {"similarity": 0.7552, "filename": "PRIV-3917"}, {"similarity": 0.7424, "filename": "PRIV-4220"}, {"similarity": 0.7389, "filename": "GKM-3732"}, {"similarity": 0.7334, "filename": "NM-3096"}, {"similarity": 0.733, "filename": "GKM-3696"}, {"similarity": 0.7298, "filename": "PRIV-3928"}, {"similarity": 0.7281, "filename": "GKM-3543"}, {"similarity": 0.727, "filename": "GKM-3784"}, {"similarity": 0.7218, "filename": "PRIV-4703"}, {"similarity": 0.7217, "filename": "PRIV-4150"}, {"similarity": 0.72, "filename": "PRIV-4242"}, {"similarity": 0.7198, "filename": "PRIV-4425"}, {"similarity": 0.7197, "filename": "PRIV-4688"}, {"similarity": 0.7187, "filename": "GKM-3669"}, {"similarity": 0.7187, "filename": "NM-3112"}, {"similarity": 0.7174, "filename": "PRIV-4591"}, {"similarity": 0.7163, "filename": "GKM-3775"}, {"similarity": 0.7155, "filename": "GKM-3461"}, {"similarity": 0.7149, "filename": "PRIV-4752"}, {"similarity": 0.714, "filename": "GKM-3596"}, {"similarity": 0.7127, "filename": "GKM-3590"}, {"similarity": 0.7123, "filename": "PRIV-4618"}, {"similarity": 0.7119, "filename": "PRIV-4206"}, {"similarity": 0.7107, "filename": "PRIV-4157"}, {"similarity": 0.7105, "filename": "NM-3091"}, {"similarity": 0.7096, "filename": "PRIV-4019"}]