[{"filename": "PRIV-4589", "similarity": 1.0}, {"filename": "GKM-3831", "similarity": 0.7887}, {"filename": "PRIV-4619", "similarity": 0.7847}, {"filename": "PRIV-3932", "similarity": 0.7729}, {"filename": "PRIV-4582", "similarity": 0.771}, {"filename": "PRIV-4051", "similarity": 0.763}, {"filename": "PRIV-4593", "similarity": 0.7626}, {"filename": "PRIV-4570", "similarity": 0.7572}, {"filename": "PRIV-4466", "similarity": 0.7545}, {"filename": "nkm-18", "similarity": 0.7543}, {"filename": "PRIV-4477", "similarity": 0.7515}, {"filename": "PRIV-4591", "similarity": 0.7409}, {"filename": "PRIV-4391", "similarity": 0.7366}, {"filename": "PRIV-4633", "similarity": 0.7346}, {"filename": "PRIV-4483", "similarity": 0.7327}, {"filename": "PRIV-4588", "similarity": 0.7325}, {"filename": "PRIV-4590", "similarity": 0.7298}, {"filename": "PRIV-4592", "similarity": 0.7283}, {"filename": "PRIV-4381", "similarity": 0.7282}, {"filename": "nkm-11", "similarity": 0.7268}, {"filename": "PRIV-4480", "similarity": 0.7264}, {"filename": "PRIV-4585", "similarity": 0.7255}, {"filename": "PRIV-4346", "similarity": 0.7238}, {"filename": "PRIV-4626", "similarity": 0.7218}, {"filename": "PRIV-4583", "similarity": 0.7148}, {"filename": "PRIV-4362", "similarity": 0.7128}, {"filename": "PRIV-4490", "similarity": 0.7127}, {"filename": "PRIV-4614", "similarity": 0.7121}, {"filename": "PRIV-4618", "similarity": 0.7117}, {"filename": "GKM-3589", "similarity": 0.7099}]