[{"similarity": 1.0, "filename": "PRIV-3994"}, {"similarity": 0.7532, "filename": "NM-3268"}, {"similarity": 0.6986, "filename": "NM-3187"}, {"similarity": 0.6873, "filename": "GKM-3490"}, {"similarity": 0.6836, "filename": "PRIV-3987"}, {"similarity": 0.676, "filename": "GKM-3680"}, {"similarity": 0.676, "filename": "GKM-3751"}, {"similarity": 0.675, "filename": "GKM-3523"}, {"similarity": 0.6735, "filename": "GKM-3525"}, {"similarity": 0.6728, "filename": "GKM-3502"}, {"similarity": 0.6723, "filename": "NM-3262"}, {"similarity": 0.6714, "filename": "NM-3191"}, {"similarity": 0.6713, "filename": "GKM-3608"}, {"similarity": 0.6704, "filename": "GKM-3695"}, {"similarity": 0.6695, "filename": "GKM-3828"}, {"similarity": 0.6683, "filename": "NM-3267"}, {"similarity": 0.6663, "filename": "GKM-3836"}, {"similarity": 0.6644, "filename": "GKM-3676"}, {"similarity": 0.664, "filename": "GUB-3387"}, {"similarity": 0.6635, "filename": "GKM-3509"}, {"similarity": 0.6634, "filename": "NM-3249"}, {"similarity": 0.662, "filename": "GKM-3512"}, {"similarity": 0.6619, "filename": "GKM-3690"}, {"similarity": 0.6605, "filename": "GKM-3542"}, {"similarity": 0.6592, "filename": "GKM-3684"}, {"similarity": 0.6592, "filename": "GKM-3546"}, {"similarity": 0.6576, "filename": "GKM-3516"}, {"similarity": 0.6566, "filename": "GKM-3515"}, {"similarity": 0.6562, "filename": "NM-3272"}, {"similarity": 0.656, "filename": "GKM-3831"}]