[{"similarity": 1.0, "filename": "PRIV-4421"}, {"similarity": 0.9103, "filename": "GKM-3571"}, {"similarity": 0.6587, "filename": "PRIV-4615"}, {"similarity": 0.6581, "filename": "PRIV-4431"}, {"similarity": 0.6522, "filename": "PRIV-4114"}, {"similarity": 0.6484, "filename": "PRIV-4323"}, {"similarity": 0.6446, "filename": "PRIV-4505"}, {"similarity": 0.6369, "filename": "PRIV-3981"}, {"similarity": 0.6273, "filename": "PRIV-4700"}, {"similarity": 0.6258, "filename": "PRIV-4744"}, {"similarity": 0.6232, "filename": "GKM-3615"}, {"similarity": 0.6193, "filename": "NM-3132"}, {"similarity": 0.619, "filename": "GKM-3494"}, {"similarity": 0.6154, "filename": "GKM-3539"}, {"similarity": 0.615, "filename": "PRIV-3989"}, {"similarity": 0.6138, "filename": "GKM-3600"}, {"similarity": 0.6135, "filename": "PRIV-4292"}, {"similarity": 0.606, "filename": "PRIV-4424"}, {"similarity": 0.6047, "filename": "GKM-3620"}, {"similarity": 0.6035, "filename": "PRIV-3979"}, {"similarity": 0.6007, "filename": "GKM-3817"}, {"similarity": 0.6005, "filename": "PRIV-4686"}, {"similarity": 0.5987, "filename": "PRIV-4658"}, {"similarity": 0.5981, "filename": "PRIV-4665"}, {"similarity": 0.5978, "filename": "NM-3135"}, {"similarity": 0.5976, "filename": "PRIV-4398"}, {"similarity": 0.5967, "filename": "PRIV-4671"}, {"similarity": 0.5966, "filename": "PRIV-3982"}, {"similarity": 0.5956, "filename": "PRIV-4585"}, {"similarity": 0.5954, "filename": "NM-3119"}]