[{"filename": "GUB-84", "similarity": 1.0}, {"filename": "GUB-154", "similarity": 0.8298}, {"filename": "GUB-76", "similarity": 0.7831}, {"filename": "GUB-70", "similarity": 0.781}, {"filename": "GUB-68", "similarity": 0.775}, {"filename": "GUB-208", "similarity": 0.7748}, {"filename": "GUB-80", "similarity": 0.7712}, {"filename": "GUB-254", "similarity": 0.7512}, {"filename": "GUB-30", "similarity": 0.7495}, {"filename": "GUB-72", "similarity": 0.7437}, {"filename": "GUB-74", "similarity": 0.7409}, {"filename": "GUB-152", "similarity": 0.7317}, {"filename": "GUB-258", "similarity": 0.7291}, {"filename": "GUB-82", "similarity": 0.7289}, {"filename": "GUB-200", "similarity": 0.7286}, {"filename": "GUB-272", "similarity": 0.7268}, {"filename": "GUB-56", "similarity": 0.7263}, {"filename": "GUB-262", "similarity": 0.7256}, {"filename": "GUB-66", "similarity": 0.7223}, {"filename": "GUB-140", "similarity": 0.722}, {"filename": "GUB-260", "similarity": 0.7186}, {"filename": "GUB-132", "similarity": 0.7161}, {"filename": "GUB-146", "similarity": 0.7117}, {"filename": "GUB-270", "similarity": 0.7097}, {"filename": "GUB-198", "similarity": 0.7075}, {"filename": "GUB-212", "similarity": 0.7057}, {"filename": "GUB-138", "similarity": 0.7005}, {"filename": "GUB-202", "similarity": 0.6983}, {"filename": "GUB-210", "similarity": 0.697}, {"filename": "GUB-110", "similarity": 0.6966}]